ghfetch.py
app/__init__.py
app/__main__.py
app/application.py
ghfetch-0.1.1.dist-info/LICENSE
ghfetch-0.1.1.dist-info/METADATA
ghfetch-0.1.1.dist-info/WHEEL
ghfetch-0.1.1.dist-info/entry_points.txt
ghfetch-0.1.1.dist-info/top_level.txt
ghfetch-0.1.1.dist-info/RECORD
